{
  "type": "FeatureCollection",
  "features": [
    {
      "type": "Feature",
      "geometry": {
        "type": "Point",
        "coordinates": [
          -71.139795,
          42.23739
        ]
      },
      "properties": {
        "yard": "Ctwn",
        "address": "21 Industrial Dr, Boston, MA, 02136"
      }
    },
    {
      "type": "Feature",
      "geometry": {
        "type": "Point",
        "coordinates": [
          -71.057577,
          42.307069
        ]
      },
      "properties": {
        "yard": "Read",
        "address": "10-34 Freeport St, Dorchester, MA, 02125"
      }
    },
    {
      "type": "Feature",
      "geometry": {
        "type": "Point",
        "coordinates": [
          -71.075801,
          42.382205
        ]
      },
      "properties": {
        "yard": "Wash",
        "address": "60-66 Cambridge Street, Boston, MA, 02129"
      }
    },
    {
      "type": "Feature",
      "geometry": {
        "type": "Point",
        "coordinates": [
          -71.080309,
          42.333189
        ]
      },
      "properties": {
        "yard": "Frpt",
        "address": "2000 Washington Street, Boston, MA, 02119"
      }
    }
  ]
}